{
  "name": "Український",
  "common": {
    "close": "Закривати",
    "cancel": "Скасування",
    "delete": "Видалити",
    "download": "Скачати",
    "loading": "Завантаження…",
    "downloading": "Скачування…"
  },
  "recording": {
    "delete": "Видалити запис",
    "recording_id": "ID Записи",
    "delete_modal": {
      "header": "Ви впевнені, що хочете видалити цей запис?",
      "subtext": "Ця дія незворотна, і ніхто не зможе допомогти вам повернути його назад."
    }
  },
  "download": {
    "sections": {
      "downloads": "Завантаження",
      "avatars": "Аватарки",
      "mt": "Мульти-трек",
      "st": "Одиночний мікшований трек",
      "stsm": "Одиночний трек інтелектуальне мікшування",
      "local_processing": "Локальна обробка"
    },
    "format_buttons": {
      "audacity": "Проект Audacity",
      "win_executable": "Додаток Windows",
      "unix_script": "Скрипт Unix",
      "other": "Інше"
    },
    "ennuizel_modal": {
      "header": "Остерігайтеся червоних кнопок!",
      "description": "Кнопки з червоною рамкою вимагають обробки звуку у вашому браузері за допомогою Ennuizel. Залежно від вашого браузера він може не підтримуватися або займати багато оперативної пам'яті для обробки вашого запису. Якщо у вас виникнуть будь-які проблеми, виберіть інший формат.",
      "confirm": "Я розумію"
    }
  },
  "avatar_overlays": {
    "options": {
      "bg": "Колір фону",
      "fg": "Колір обведення",
      "transparent": "Прозорий фон",
      "format": "Формат"
    }
  },
  "footer": {
    "build": "Версія"
  }
}
